{
    "data": [
        {
            "source_id": 1,
            "tevcat_id": 227,
            "discoverer": "veritas",
            "common_name": "CTA 1",
            "papers": "2013ApJ...764...38A",
            "tgevcat_name": "TeV J0006+7259",
            "classes": [
                "pwn",
                "snr"
            ],
            "tgevcat_id": 1,
            "gamma_names": [
                "VER J0006+729"
            ],
            "tevcat2_id": "rC5JCj",
            "tevcat_name": "TeV J0006+729",
            "where": "gal",
            "other_names": [
                "SNR G119.5+10.2"
            ],
            "discovery_date": "",
            "notes": "",
            "seen_by": [
                "veritas"
            ]
        },
        {
            "source_id": 2,
            "tevcat_id": 213,
            "discoverer": "hess",
            "common_name": "SHBL J001355.9-185406",
            "papers": "2013A&A...554A..72H",
            "tgevcat_name": "TeV J0013-1853",
            "classes": [
                "hbl"
            ],
            "tgevcat_id": 2,
            "gamma_names": [],
            "tevcat2_id": "70hRXZ",
            "tevcat_name": "TeV J0013-188",
            "where": "egal",
            "other_names": [],
            "discovery_date": "",
            "notes": "",
            "seen_by": [
                "hess"
            ]
        },
        {
            "source_id": 3,
            "tevcat_id": 209,
            "discoverer": "veritas",
            "common_name": "Tycho SNR",
            "papers": "2011ApJ...730L..20A",
            "tgevcat_name": "TeV J0025+6410",
            "classes": [
                "snr"
            ],
            "tgevcat_id": 3,
            "gamma_names": [],
            "tevcat2_id": "xCyAjF",
            "tevcat_name": "TeV J0025+641",
            "where": "gal",
            "other_names": [
                "SNR G120.1+1.4",
                "3C10",
                "SN1572"
            ],
            "discovery_date": "",
            "notes": "",
            "seen_by": [
                "veritas"
            ]
        },
        {
            "source_id": 4,
            "tevcat_id": 239,
            "discoverer": "hess",
            "common_name": "KUV 00311-1938",
            "papers": "2012AIPC.1505..490B",
            "tgevcat_name": "TeV J0033-1921",
            "classes": [
                "hbl"
            ],
            "tgevcat_id": 4,
            "gamma_names": [],
            "tevcat2_id": "PKJZqs",
            "tevcat_name": "TeV J0033-193",
            "where": "egal",
            "other_names": [],
            "discovery_date": "",
            "notes": "",
            "seen_by": [
                "hess"
            ]
        },
        {
            "source_id": 5,
            "tevcat_id": 229,
            "discoverer": "magic",
            "common_name": "1ES 0033+595",
            "papers": "2015MNRAS.446..217A",
            "tgevcat_name": "TeV J0035+5947",
            "classes": [
                "hbl"
            ],
            "tgevcat_id": 5,
            "gamma_names": [],
            "tevcat2_id": "eNYfrm",
            "tevcat_name": "TeV J0035+598",
            "where": "egal",
            "other_names": [],
            "discovery_date": "",
            "notes": "",
            "seen_by": [
                "magic"
            ]
        },
        {
            "source_id": 6,
            "tevcat_id": 195,
            "discoverer": "hess",
            "common_name": "NGC 253",
            "papers": "2009Sci...326.1080A,2012ApJ...757..158A",
            "tgevcat_name": "TeV J0047-2517",
            "classes": [
                "galaxy"
            ],
            "tgevcat_id": 6,
            "gamma_names": [],
            "tevcat2_id": "sK2rQU",
            "tevcat_name": "TeV J0047-253",
            "where": "egal",
            "other_names": [],
            "discovery_date": "",
            "notes": "",
            "seen_by": [
                "hess"
            ]
        },
        {
            "source_id": 7,
            "tevcat_id": 244,
            "discoverer": "magic",
            "common_name": "RGB J0136+391",
            "papers": "2012AIPC.1505..186M",
            "tgevcat_name": "TeV J0136+3905",
            "classes": [
                "hbl"
            ],
            "tgevcat_id": 7,
            "gamma_names": [],
            "tevcat2_id": "7WhQrw",
            "tevcat_name": "TeV J0136+391",
            "where": "egal",
            "other_names": [
                "B3 0133+388",
                "1RXS J013632.9+390556"
            ],
            "discovery_date": "",
            "notes": "Source announced at Gamma 2012.\nNo proceeding or paper yet?\nCheck 2012AIPC.1505..186M\n",
            "seen_by": [
                "magic"
            ]
        },
        {
            "source_id": 8,
            "tevcat_id": 156,
            "discoverer": "hess",
            "common_name": "RGB J0152+017",
            "papers": "2008A&A...481L.103A,2008bves.confE..46L",
            "tgevcat_name": "TeV J0152+0146",
            "classes": [
                "hbl"
            ],
            "tgevcat_id": 8,
            "gamma_names": [],
            "tevcat2_id": "tKGVcC",
            "tevcat_name": "TeV J0152+017",
            "where": "egal",
            "other_names": [
                "RXJ0152.6+0147"
            ],
            "discovery_date": "",
            "notes": "",
            "seen_by": [
                "hess"
            ]
        },
        {
            "source_id": 9,
            "tevcat_id": 252,
            "discoverer": "hess",
            "common_name": "3C 58",
            "papers": "2014A&A...567L...8A",
            "tgevcat_name": "TeV J0205+6451",
            "classes": [
                "pwn"
            ],
            "tgevcat_id": 9,
            "gamma_names": [],
            "tevcat2_id": "2I2TuY",
            "tevcat_name": "TeV J0209+648",
            "where": "gal",
            "other_names": [],
            "discovery_date": "",
            "notes": "",
            "seen_by": [
                "hess"
            ]
        },
        {
            "source_id": 10,
            "tevcat_id": 254,
            "discoverer": "magic",
            "common_name": "S3 0218+35",
            "papers": "2016JPhCS.718e2022M",
            "tgevcat_name": "TeV J0221+3556",
            "classes": [
                "blazar"
            ],
            "tgevcat_id": 10,
            "gamma_names": [],
            "tevcat2_id": "hJnA37",
            "tevcat_name": "TeV J0218+359",
            "where": "egal",
            "other_names": [
                "B2 0218+35"
            ],
            "discovery_date": "",
            "notes": "",
            "seen_by": [
                "magic"
            ]
        },
        {
            "source_id": 11,
            "tevcat_id": 119,
            "discoverer": "crimea",
            "common_name": "3C 66A",
            "papers": "2011ApJ...726...58A,2009ApJ...693L.104A",
            "tgevcat_name": "TeV J0222+4302",
            "classes": [
                "ibl"
            ],
            "tgevcat_id": 11,
            "gamma_names": [],
            "tevcat2_id": "J01xzR",
            "tevcat_name": "TeV J0222+430",
            "where": "egal",
            "other_names": [
                "B2 0218+35"
            ],
            "discovery_date": "",
            "notes": "",
            "seen_by": [
                "magic",
                "veritas",
                "crimea"
            ]
        },
        {
            "source_id": 12,
            "tevcat_id": 138,
            "discoverer": "magic",
            "common_name": "MAGIC J0223+403",
            "papers": "2009ApJ...692L..29A",
            "tgevcat_name": "TeV J0223+4259",
            "classes": [
                "unid"
            ],
            "tgevcat_id": 12,
            "gamma_names": [
                "MAGIC J0223+403"
            ],
            "tevcat2_id": "y6gVxa",
            "tevcat_name": "TeV J0223+430",
            "where": "unid",
            "other_names": [
                "3C 66A/B Region"
            ],
            "discovery_date": "",
            "notes": "",
            "seen_by": [
                "magic"
            ]
        },
        {
            "source_id": 13,
            "tevcat_id": 130,
            "discoverer": "hess",
            "common_name": "1ES 0229+200",
            "papers": "2007A&A...475L...9A,2011arXiv1110.0038",
            "tgevcat_name": "TeV J0232+2016",
            "classes": [
                "hbl"
            ],
            "tgevcat_id": 13,
            "gamma_names": [],
            "tevcat2_id": "pVNsSZ",
            "tevcat_name": "TeV J0232+202",
            "where": "egal",
            "other_names": [],
            "discovery_date": "",
            "notes": "",
            "seen_by": [
                "hess",
                "veritas"
            ]
        },
        {
            "source_id": 14,
            "tevcat_id": 89,
            "discoverer": "magic",
            "common_name": "LS I +61 303",
            "papers": "2006Sci...312.1771A,2008ApJ...679.1427A",
            "tgevcat_name": "TeV J0240+6115",
            "classes": [
                "bin"
            ],
            "tgevcat_id": 14,
            "gamma_names": [],
            "tevcat2_id": "fW749W",
            "tevcat_name": "TeV J0240+612",
            "where": "gal",
            "other_names": [],
            "discovery_date": "",
            "notes": "",
            "seen_by": [
                "veritas",
                "magic"
            ]
        },
        {
            "source_id": 15,
            "tevcat_id": 240,
            "discoverer": "hess",
            "common_name": "PKS 0301-243",
            "papers": "2013A&A...559A.136H",
            "tgevcat_name": "TeV J0303-2407",
            "classes": [
                "hbl"
            ],
            "tgevcat_id": 15,
            "gamma_names": [],
            "tevcat2_id": "5puKGr",
            "tevcat_name": "TeV J0303-241",
            "where": "egal",
            "other_names": [],
            "discovery_date": "",
            "notes": "",
            "seen_by": [
                "hess"
            ]
        },
        {
            "source_id": 16,
            "tevcat_id": 208,
            "discoverer": "magic",
            "common_name": "IC 310",
            "papers": "2014A&A...563A..91A",
            "tgevcat_name": "TeV J0316+4119",
            "classes": [
                "hbl"
            ],
            "tgevcat_id": 16,
            "gamma_names": [
                "MAGIC J0317+413"
            ],
            "tevcat2_id": "hooot9",
            "tevcat_name": "TeV J0316+413",
            "where": "egal",
            "other_names": [],
            "discovery_date": "",
            "notes": "",
            "seen_by": [
                "magic"
            ]
        },
        {
            "source_id": 17,
            "tevcat_id": 198,
            "discoverer": "veritas",
            "common_name": "RBS 0413",
            "papers": "2012ApJ...750...94A",
            "tgevcat_name": "TeV J0319+1845",
            "classes": [
                "hbl"
            ],
            "tgevcat_id": 17,
            "gamma_names": [],
            "tevcat2_id": "p26X9Z",
            "tevcat_name": "TeV J0319+187",
            "where": "egal",
            "other_names": [
                "RBS 0413",
                "EXO 0317.0+1834",
                "1E 0317.0+1835"
            ],
            "discovery_date": "",
            "notes": "",
            "seen_by": [
                "veritas"
            ]
        },
        {
            "source_id": 18,
            "tevcat_id": 212,
            "discoverer": "magic",
            "common_name": "NGC 1275",
            "papers": "2012A&A...539L...2A,2016A&A...589A..33A",
            "tgevcat_name": "TeV J0319+4130",
            "classes": [
                "fri"
            ],
            "tgevcat_id": 18,
            "gamma_names": [],
            "tevcat2_id": "9dfnMH",
            "tevcat_name": "TeV J0319+415",
            "where": "egal",
            "other_names": [],
            "discovery_date": "",
            "notes": "",
            "seen_by": [
                "magic"
            ]
        },
        {
            "source_id": 19,
            "tevcat_id": 147,
            "discoverer": "hess",
            "common_name": "1ES 0347-121",
            "papers": "2007A&A...473L..25A",
            "tgevcat_name": "TeV J0349-1158",
            "classes": [
                "hbl"
            ],
            "tgevcat_id": 19,
            "gamma_names": [],
            "tevcat2_id": "rWyLLM",
            "tevcat_name": "TeV J0349-119",
            "where": "egal",
            "other_names": [],
            "discovery_date": "",
            "notes": "",
            "seen_by": [
                "hess"
            ]
        },
        {
            "source_id": 20,
            "tevcat_id": 199,
            "discoverer": "hess",
            "common_name": "1ES 0414+009",
            "papers": "2013arXiv1307.7051M,2012ApJ...755..118A,2012A&A...538A.103H",
            "tgevcat_name": "TeV J0416+0105",
            "classes": [
                "hbl"
            ],
            "tgevcat_id": 20,
            "gamma_names": [],
            "tevcat2_id": "hKCHxG",
            "tevcat_name": "TeV J0416+010",
            "where": "egal",
            "other_names": [],
            "discovery_date": "",
            "notes": "",
            "seen_by": [
                "hess",
                "veritas"
            ]
        },
        {
            "source_id": 21,
            "tevcat_id": 203,
            "discoverer": "hess",
            "common_name": "PKS 0447-439",
            "papers": "2013A&A...552A.118H",
            "tgevcat_name": "TeV J0449-4350",
            "classes": [
                "hbl"
            ],
            "tgevcat_id": 21,
            "gamma_names": [],
            "tevcat2_id": "ewJQZd",
            "tevcat_name": "TeV J0449-438",
            "where": "egal",
            "other_names": [],
            "discovery_date": "",
            "notes": "",
            "seen_by": [
                "hess"
            ]
        },
        {
            "source_id": 22,
            "tevcat_id": 200,
            "discoverer": "veritas",
            "common_name": "1ES 0502+675",
            "papers": "2011arXiv1110.0040W,atel-2301",
            "tgevcat_name": "TeV J0507+6737",
            "classes": [
                "hbl"
            ],
            "tgevcat_id": 22,
            "gamma_names": [],
            "tevcat2_id": "1G0nr7",
            "tevcat_name": "TeV J0507+676",
            "where": "egal",
            "other_names": [],
            "discovery_date": "",
            "notes": "",
            "seen_by": [
                "veritas"
            ]
        },
        {
            "source_id": 23,
            "tevcat_id": 196,
            "discoverer": "veritas",
            "common_name": "RGB J0521+212",
            "papers": "2013ApJ...776...69A,atel-2309",
            "tgevcat_name": "TeV J0521+2112",
            "classes": [
                "ibl"
            ],
            "tgevcat_id": 23,
            "gamma_names": [
                "VER J0521+211"
            ],
            "tevcat2_id": "ILT7om",
            "tevcat_name": "TeV J0521+211",
            "where": "egal",
            "other_names": [],
            "discovery_date": "",
            "notes": "",
            "seen_by": [
                "veritas"
            ]
        },
        {
            "source_id": 24,
            "tevcat_id": 256,
            "discoverer": "hess",
            "common_name": "LMC N132D",
            "papers": "2015Sci...347..406H",
            "tgevcat_name": "TeV J0525-6938",
            "classes": [
                "snr",
                "mc"
            ],
            "tgevcat_id": 24,
            "gamma_names": [],
            "tevcat2_id": "z30txh",
            "tevcat_name": "TeV J0525-696",
            "where": "egal",
            "other_names": [
                "SNR J052501-693842"
            ],
            "discovery_date": "",
            "notes": "",
            "seen_by": [
                "hess"
            ]
        },
        {
            "source_id": 25,
            "tevcat_id": 74,
            "discoverer": "hess",
            "common_name": "Crab nebula",
            "papers": "2006A&A...457..899A,2004ApJ...614..897A",
            "tgevcat_name": "TeV J0534+2200",
            "classes": [
                "pwn"
            ],
            "tgevcat_id": 25,
            "gamma_names": [],
            "tevcat2_id": "BlJI6q",
            "tevcat_name": "TeV J0534+220",
            "where": "gal",
            "other_names": [
                "G184.6-5.8",
                "3C 144",
                "SN 1054"
            ],
            "discovery_date": "",
            "notes": "",
            "seen_by": [
                "hess",
                "hegra",
                "magic",
                "veritas",
                "hawc"
            ]
        },
        {
            "source_id": 26,
            "tevcat_id": 255,
            "discoverer": "hess",
            "common_name": "30 Dor C",
            "papers": "2015Sci...347..406H",
            "tgevcat_name": "TeV J0535-6911",
            "classes": [
                "other"
            ],
            "tgevcat_id": 26,
            "gamma_names": [],
            "tevcat2_id": "C6fp9j",
            "tevcat_name": "TeV J0535-692",
            "where": "egal",
            "other_names": [],
            "discovery_date": "",
            "notes": "",
            "seen_by": [
                "hess"
            ]
        },
        {
            "source_id": 27,
            "tevcat_id": 236,
            "discoverer": "hess",
            "common_name": "N 157B",
            "papers": "2012A&A...545L...2H,2015Sci...347..406H",
            "tgevcat_name": "TeV J0537-6909",
            "classes": [
                "pwn"
            ],
            "tgevcat_id": 27,
            "gamma_names": [
                "HESS J0537-691"
            ],
            "tevcat2_id": "8hS5e7",
            "tevcat_name": "TeV J0537-691",
            "where": "egal",
            "other_names": [
                "LHA 120-N 157B",
                "PSR J0537-6910"
            ],
            "discovery_date": "",
            "notes": "",
            "seen_by": [
                "hess"
            ]
        },
        {
            "source_id": 28,
            "tevcat_id": 133,
            "discoverer": "hess",
            "common_name": "PKS 0548-322",
            "papers": "2010A&A...521A..69A",
            "tgevcat_name": "TeV J0550-3216",
            "classes": [
                "hbl"
            ],
            "tgevcat_id": 28,
            "gamma_names": [],
            "tevcat2_id": "U09cDa",
            "tevcat_name": "TeV J0550-322",
            "where": "egal",
            "other_names": [
                "H 0548-322",
                "1ES 0548-322"
            ],
            "discovery_date": "",
            "notes": "",
            "seen_by": [
                "hess"
            ]
        },
        {
            "source_id": 29,
            "tevcat_id": 120,
            "discoverer": "magic",
            "common_name": "IC 443",
            "papers": "2007ApJ...664L..87A,2009ApJ...700L.127A,2009ApJ...698L.133A",
            "tgevcat_name": "TeV J0616+2230",
            "classes": [
                "snr"
            ],
            "tgevcat_id": 29,
            "gamma_names": [
                "MAGIC 0616+223"
            ],
            "tevcat2_id": "9xMcgD",
            "tevcat_name": "TeV J0616+225",
            "where": "gal",
            "other_names": [
                "3C 157",
                "SNR 189.1+03.0"
            ],
            "discovery_date": "",
            "notes": "",
            "seen_by": [
                "magic",
                "veritas",
                "milagro"
            ]
        },
        {
            "source_id": 30,
            "tevcat_id": 134,
            "discoverer": "hess",
            "common_name": "HESS J0632+057",
            "papers": "2007A&A...469L...1A,2009ApJ...690L.101H,2012ApJ...754L..10A",
            "tgevcat_name": "TeV J0632+0548",
            "classes": [
                "bin"
            ],
            "tgevcat_id": 30,
            "gamma_names": [
                "HESS J0632+057",
                "VER J0633+057"
            ],
            "tevcat2_id": "jPeNQq",
            "tevcat_name": "TeV J0632+058",
            "where": "gal",
            "other_names": [
                "HD 259440"
            ],
            "discovery_date": "",
            "notes": "",
            "seen_by": [
                "hess",
                "veritas",
                "magic"
            ]
        },
        {
            "source_id": 31,
            "tevcat_id": 177,
            "discoverer": "",
            "common_name": "",
            "papers": "todo",
            "tgevcat_name": "TeV J0632+1722",
            "classes": "",
            "tgevcat_id": 31,
            "gamma_names": "",
            "tevcat2_id": "66DvGb",
            "tevcat_name": "TeV J0632+173",
            "where": "",
            "other_names": "",
            "discovery_date": "",
            "notes": "",
            "seen_by": ""
        },
        {
            "source_id": 32,
            "tevcat_id": 207,
            "discoverer": "",
            "common_name": "",
            "papers": "",
            "tgevcat_name": "TeV J0648+1516",
            "classes": "",
            "tgevcat_id": 32,
            "gamma_names": "",
            "tevcat2_id": "0WgN2s",
            "tevcat_name": "TeV J0648+152",
            "where": "",
            "other_names": "",
            "discovery_date": "",
            "notes": "",
            "seen_by": ""
        },
        {
            "source_id": 33,
            "tevcat_id": 238,
            "discoverer": "",
            "common_name": "",
            "papers": "",
            "tgevcat_name": "TeV J0650+2503",
            "classes": "",
            "tgevcat_id": 33,
            "gamma_names": "",
            "tevcat2_id": "zp72d7",
            "tevcat_name": "TeV J0650+250",
            "where": "",
            "other_names": "",
            "discovery_date": "",
            "notes": "",
            "seen_by": ""
        },
        {
            "source_id": 34,
            "tevcat_id": 173,
            "discoverer": "",
            "common_name": "",
            "papers": "",
            "tgevcat_name": "TeV J0710+5909",
            "classes": "",
            "tgevcat_id": 34,
            "gamma_names": "",
            "tevcat2_id": "vejQq8",
            "tevcat_name": "TeV J0710+591",
            "where": "",
            "other_names": "",
            "discovery_date": "",
            "notes": "",
            "seen_by": ""
        },
        {
            "source_id": 35,
            "tevcat_id": 172,
            "discoverer": "",
            "common_name": "",
            "papers": "",
            "tgevcat_name": "TeV J0721+7120",
            "classes": "",
            "tgevcat_id": 35,
            "gamma_names": "",
            "tevcat2_id": "vDwoU3",
            "tevcat_name": "TeV J0721+713",
            "where": "",
            "other_names": "",
            "discovery_date": "",
            "notes": "",
            "seen_by": ""
        },
        {
            "source_id": 36,
            "tevcat_id": 160,
            "discoverer": "",
            "common_name": "",
            "papers": "",
            "tgevcat_name": "TeV J0809+5219",
            "classes": "",
            "tgevcat_id": 36,
            "gamma_names": "",
            "tevcat2_id": "kIwUzI",
            "tevcat_name": "TeV J0809+523",
            "where": "",
            "other_names": "",
            "discovery_date": "",
            "notes": "",
            "seen_by": ""
        },
        {
            "source_id": 37,
            "tevcat_id": 86,
            "discoverer": "hess",
            "common_name": "Vela X",
            "papers": "2012A&A...548A..38A,2006A&A...448L..43A",
            "tgevcat_name": "TeV J0835-4536",
            "classes": [
                "pwn"
            ],
            "tgevcat_id": 37,
            "gamma_names": [
                "HESS J0835-455"
            ],
            "tevcat2_id": "yVoFOS",
            "tevcat_name": "TeV J0835-456",
            "where": "gal",
            "other_names": [],
            "discovery_date": "todo",
            "notes": "",
            "seen_by": [
                "hess"
            ]
        },
        {
            "source_id": 38,
            "tevcat_id": 249,
            "discoverer": "",
            "common_name": "",
            "papers": "",
            "tgevcat_name": "TeV J0847+1133",
            "classes": "",
            "tgevcat_id": 38,
            "gamma_names": "",
            "tevcat2_id": "nhyiXQ",
            "tevcat_name": "TeV J0847+115",
            "where": "",
            "other_names": "",
            "discovery_date": "",
            "notes": "",
            "seen_by": ""
        },
        {
            "source_id": 39,
            "tevcat_id": 98,
            "discoverer": "cangaroo",
            "common_name": "Vela Junior",
            "papers": "2005A&A...437L...7A,2007ApJ...661..236A",
            "tgevcat_name": "TeV J0852-4622",
            "classes": [
                "snr"
            ],
            "tgevcat_id": 39,
            "gamma_names": [
                "HESS J0852-463"
            ],
            "tevcat2_id": "FfpuKQ",
            "tevcat_name": "TeV J0852-463",
            "where": "gal",
            "other_names": [
                "RX J0852.0-4622"
            ],
            "discovery_date": "todo",
            "notes": "",
            "seen_by": [
                "cangaroo",
                "hess"
            ]
        },
        {
            "source_id": 40,
            "tevcat_id": 194,
            "discoverer": "",
            "common_name": "",
            "papers": "",
            "tgevcat_name": "TeV J0955+6940",
            "classes": "",
            "tgevcat_id": 40,
            "gamma_names": "",
            "tevcat2_id": "wN7SNs",
            "tevcat_name": "TeV J0955+696",
            "where": "",
            "other_names": "",
            "discovery_date": "",
            "notes": "",
            "seen_by": ""
        },
        {
            "source_id": 41,
            "tevcat_id": 258,
            "discoverer": "",
            "common_name": "",
            "papers": "",
            "tgevcat_name": "TeV J0958+6533",
            "classes": "",
            "tgevcat_id": 41,
            "gamma_names": "",
            "tevcat2_id": "",
            "tevcat_name": "TeV J0958+655",
            "where": "",
            "other_names": "",
            "discovery_date": "",
            "notes": "",
            "seen_by": ""
        },
        {
            "source_id": 42,
            "tevcat_id": 215,
            "discoverer": "",
            "common_name": "",
            "papers": "",
            "tgevcat_name": "TeV J1010-3118",
            "classes": "",
            "tgevcat_id": 42,
            "gamma_names": "",
            "tevcat2_id": "7fxWYa",
            "tevcat_name": "TeV J1010-313",
            "where": "",
            "other_names": "",
            "discovery_date": "",
            "notes": "",
            "seen_by": ""
        },
        {
            "source_id": 43,
            "tevcat_id": 153,
            "discoverer": "",
            "common_name": "",
            "papers": "",
            "tgevcat_name": "TeV J1015+4926",
            "classes": "",
            "tgevcat_id": 43,
            "gamma_names": "",
            "tevcat2_id": "agykYI",
            "tevcat_name": "TeV J1015+494",
            "where": "",
            "other_names": "",
            "discovery_date": "",
            "notes": "",
            "seen_by": ""
        },
        {
            "source_id": 44,
            "tevcat_id": 260,
            "discoverer": "",
            "common_name": "",
            "papers": "",
            "tgevcat_name": "TeV J1016-5858",
            "classes": "",
            "tgevcat_id": 44,
            "gamma_names": "",
            "tevcat2_id": "QhYho8",
            "tevcat_name": "TeV J1016-589",
            "where": "",
            "other_names": "",
            "discovery_date": "",
            "notes": "",
            "seen_by": ""
        },
        {
            "source_id": 45,
            "tevcat_id": 237,
            "discoverer": "",
            "common_name": "",
            "papers": "",
            "tgevcat_name": "TeV J1018-5856",
            "classes": "",
            "tgevcat_id": 45,
            "gamma_names": "",
            "tevcat2_id": "5FlzLA",
            "tevcat_name": "TeV J1018-589",
            "where": "",
            "other_names": "",
            "discovery_date": "",
            "notes": "",
            "seen_by": ""
        },
        {
            "source_id": 46,
            "tevcat_id": 132,
            "discoverer": "",
            "common_name": "",
            "papers": "2007A&A...467.1075A,2011A&A...525A..46H",
            "tgevcat_name": "TeV J1023-5747",
            "classes": "",
            "tgevcat_id": 46,
            "gamma_names": "",
            "tevcat2_id": "nvPEhx",
            "tevcat_name": "TeV J1023-577",
            "where": "",
            "other_names": "",
            "discovery_date": "",
            "notes": "",
            "seen_by": ""
        },
        {
            "source_id": 47,
            "tevcat_id": 220,
            "discoverer": "",
            "common_name": "",
            "papers": "",
            "tgevcat_name": "TeV J1026-5812",
            "classes": "",
            "tgevcat_id": 47,
            "gamma_names": "",
            "tevcat2_id": "UwjiUu",
            "tevcat_name": "TeV J1026-582",
            "where": "",
            "other_names": "",
            "discovery_date": "",
            "notes": "",
            "seen_by": ""
        },
        {
            "source_id": 48,
            "tevcat_id": 97,
            "discoverer": "",
            "common_name": "",
            "papers": "",
            "tgevcat_name": "TeV J1103-2329",
            "classes": "",
            "tgevcat_id": 48,
            "gamma_names": "",
            "tevcat2_id": "2Z3QTH",
            "tevcat_name": "TeV J1103-234",
            "where": "",
            "other_names": "",
            "discovery_date": "",
            "notes": "",
            "seen_by": ""
        },
        {
            "source_id": 49,
            "tevcat_id": 75,
            "discoverer": "",
            "common_name": "",
            "papers": "",
            "tgevcat_name": "TeV J1104+3811",
            "classes": "",
            "tgevcat_id": 49,
            "gamma_names": "",
            "tevcat2_id": "cIB7Uf",
            "tevcat_name": "TeV J1104+382",
            "where": "",
            "other_names": "",
            "discovery_date": "",
            "notes": "",
            "seen_by": ""
        },
        {
            "source_id": 50,
            "tevcat_id": 205,
            "discoverer": "",
            "common_name": "",
            "papers": "",
            "tgevcat_name": "TeV J1119-6124",
            "classes": "",
            "tgevcat_id": 50,
            "gamma_names": "",
            "tevcat2_id": "1wyMpL",
            "tevcat_name": "TeV J1119-614",
            "where": "",
            "other_names": "",
            "discovery_date": "",
            "notes": "",
            "seen_by": ""
        },
        {
            "source_id": 51,
            "tevcat_id": 251,
            "discoverer": "",
            "common_name": "",
            "papers": "",
            "tgevcat_name": "TeV J1136+6737",
            "classes": "",
            "tgevcat_id": 51,
            "gamma_names": "",
            "tevcat2_id": "6T4fxx",
            "tevcat_name": "TeV J1136+676",
            "where": "",
            "other_names": "",
            "discovery_date": "",
            "notes": "",
            "seen_by": ""
        },
        {
            "source_id": 52,
            "tevcat_id": 123,
            "discoverer": "",
            "common_name": "",
            "papers": "",
            "tgevcat_name": "TeV J1136+7009",
            "classes": "",
            "tgevcat_id": 52,
            "gamma_names": "",
            "tevcat2_id": "mijtir",
            "tevcat_name": "TeV J1136+701",
            "where": "",
            "other_names": "",
            "discovery_date": "",
            "notes": "",
            "seen_by": ""
        },
        {
            "source_id": 53,
            "tevcat_id": 219,
            "discoverer": "",
            "common_name": "",
            "papers": "",
            "tgevcat_name": "TeV J1217+3006",
            "classes": "",
            "tgevcat_id": 53,
            "gamma_names": "",
            "tevcat2_id": "891TG0",
            "tevcat_name": "TeV J1217+301",
            "where": "",
            "other_names": "",
            "discovery_date": "",
            "notes": "",
            "seen_by": ""
        },
        {
            "source_id": 54,
            "tevcat_id": 159,
            "discoverer": "",
            "common_name": "",
            "papers": "",
            "tgevcat_name": "TeV J1221+2813",
            "classes": "",
            "tgevcat_id": 54,
            "gamma_names": "",
            "tevcat2_id": "XQhcCi",
            "tevcat_name": "TeV J1221+282",
            "where": "",
            "other_names": "",
            "discovery_date": "",
            "notes": "",
            "seen_by": ""
        },
        {
            "source_id": 55,
            "tevcat_id": 91,
            "discoverer": "",
            "common_name": "",
            "papers": "",
            "tgevcat_name": "TeV J1221+3011",
            "classes": "",
            "tgevcat_id": 55,
            "gamma_names": "",
            "tevcat2_id": "urWmHx",
            "tevcat_name": "TeV J1221+301",
            "where": "",
            "other_names": "",
            "discovery_date": "",
            "notes": "",
            "seen_by": ""
        },
        {
            "source_id": 56,
            "tevcat_id": 210,
            "discoverer": "",
            "common_name": "",
            "papers": "",
            "tgevcat_name": "TeV J1224+2122",
            "classes": "",
            "tgevcat_id": 56,
            "gamma_names": "",
            "tevcat2_id": "dDaGC0",
            "tevcat_name": "TeV J1224+213",
            "where": "",
            "other_names": "",
            "discovery_date": "",
            "notes": "",
            "seen_by": ""
        },
        {
            "source_id": 57,
            "tevcat_id": 245,
            "discoverer": "",
            "common_name": "",
            "papers": "",
            "tgevcat_name": "TeV J1224+2436",
            "classes": "",
            "tgevcat_id": 57,
            "gamma_names": "",
            "tevcat2_id": "LpjBMP",
            "tevcat_name": "TeV J1224+246",
            "where": "",
            "other_names": "",
            "discovery_date": "",
            "notes": "",
            "seen_by": ""
        },
        {
            "source_id": 58,
            "tevcat_id": 80,
            "discoverer": "",
            "common_name": "",
            "papers": "",
            "tgevcat_name": "TeV J1230+1223",
            "classes": "",
            "tgevcat_id": 58,
            "gamma_names": "",
            "tevcat2_id": "XheKQH",
            "tevcat_name": "TeV J1230+123",
            "where": "",
            "other_names": "",
            "discovery_date": "",
            "notes": "",
            "seen_by": ""
        },
        {
            "source_id": 59,
            "tevcat_id": 166,
            "discoverer": "",
            "common_name": "",
            "papers": "",
            "tgevcat_name": "TeV J1256-0547",
            "classes": "",
            "tgevcat_id": 59,
            "gamma_names": "",
            "tevcat2_id": "YmUotO",
            "tevcat_name": "TeV J1256-057",
            "where": "",
            "other_names": "",
            "discovery_date": "",
            "notes": "",
            "seen_by": ""
        },
        {
            "source_id": 60,
            "tevcat_id": 93,
            "discoverer": "",
            "common_name": "",
            "papers": "",
            "tgevcat_name": "TeV J1302-6349",
            "classes": "",
            "tgevcat_id": 60,
            "gamma_names": "",
            "tevcat2_id": "HJQC5t",
            "tevcat_name": "TeV J1302-638",
            "where": "",
            "other_names": "",
            "discovery_date": "",
            "notes": "",
            "seen_by": ""
        },
        {
            "source_id": 61,
            "tevcat_id": 94,
            "discoverer": "",
            "common_name": "",
            "papers": "",
            "tgevcat_name": "TeV J1302-6310",
            "classes": "",
            "tgevcat_id": 61,
            "gamma_names": "",
            "tevcat2_id": "4au9RH",
            "tevcat_name": "TeV J1303-631",
            "where": "",
            "other_names": "",
            "discovery_date": "",
            "notes": "",
            "seen_by": ""
        },
        {
            "source_id": 62,
            "tevcat_id": 216,
            "discoverer": "",
            "common_name": "",
            "papers": "",
            "tgevcat_name": "TeV J1314-4235",
            "classes": "",
            "tgevcat_id": 62,
            "gamma_names": "",
            "tevcat2_id": "7uB4QE",
            "tevcat_name": "TeV J1315-426",
            "where": "",
            "other_names": "",
            "discovery_date": "",
            "notes": "",
            "seen_by": ""
        },
        {
            "source_id": 63,
            "tevcat_id": 122,
            "discoverer": "",
            "common_name": "",
            "papers": "",
            "tgevcat_name": "TeV J1325-4300",
            "classes": "",
            "tgevcat_id": 63,
            "gamma_names": "",
            "tevcat2_id": "ubPSXn",
            "tevcat_name": "TeV J1325-430",
            "where": "",
            "other_names": "",
            "discovery_date": "",
            "notes": "",
            "seen_by": ""
        },
        {
            "source_id": 64,
            "tevcat_id": 170,
            "discoverer": "",
            "common_name": "",
            "papers": "",
            "tgevcat_name": "TeV J1356-6430",
            "classes": "",
            "tgevcat_id": 64,
            "gamma_names": "",
            "tevcat2_id": "ms0x8h",
            "tevcat_name": "TeV J1356-645",
            "where": "",
            "other_names": "",
            "discovery_date": "",
            "notes": "",
            "seen_by": ""
        },
        {
            "source_id": 65,
            "tevcat_id": 125,
            "discoverer": "",
            "common_name": "",
            "papers": "",
            "tgevcat_name": "TeV J1418-6058",
            "classes": "",
            "tgevcat_id": 65,
            "gamma_names": "",
            "tevcat2_id": "r1X1KA",
            "tevcat_name": "TeV J1418-609",
            "where": "",
            "other_names": "",
            "discovery_date": "",
            "notes": "",
            "seen_by": ""
        },
        {
            "source_id": 66,
            "tevcat_id": 124,
            "discoverer": "",
            "common_name": "",
            "papers": "",
            "tgevcat_name": "TeV J1420-6045",
            "classes": "",
            "tgevcat_id": 66,
            "gamma_names": "",
            "tevcat2_id": "zUDsnw",
            "tevcat_name": "TeV J1420-607",
            "where": "",
            "other_names": "",
            "discovery_date": "",
            "notes": "",
            "seen_by": ""
        },
        {
            "source_id": 67,
            "tevcat_id": 184,
            "discoverer": "",
            "common_name": "",
            "papers": "",
            "tgevcat_name": "TeV J1427+2347",
            "classes": "",
            "tgevcat_id": 67,
            "gamma_names": "",
            "tevcat2_id": "lGHxlE",
            "tevcat_name": "TeV J1427+238",
            "where": "",
            "other_names": "",
            "discovery_date": "",
            "notes": "",
            "seen_by": ""
        },
        {
            "source_id": 68,
            "tevcat_id": 139,
            "discoverer": "",
            "common_name": "",
            "papers": "",
            "tgevcat_name": "TeV J1427-6051",
            "classes": "",
            "tgevcat_id": 68,
            "gamma_names": "",
            "tevcat2_id": "eee9un",
            "tevcat_name": "TeV J1427-608",
            "where": "",
            "other_names": "",
            "discovery_date": "",
            "notes": "",
            "seen_by": ""
        },
        {
            "source_id": 69,
            "tevcat_id": 78,
            "discoverer": "",
            "common_name": "",
            "papers": "",
            "tgevcat_name": "TeV J1428+4240",
            "classes": "",
            "tgevcat_id": 69,
            "gamma_names": "",
            "tevcat2_id": "F5cSH7",
            "tevcat_name": "TeV J1428+426",
            "where": "",
            "other_names": "",
            "discovery_date": "",
            "notes": "",
            "seen_by": ""
        },
        {
            "source_id": 70,
            "tevcat_id": 168,
            "discoverer": "",
            "common_name": "",
            "papers": "",
            "tgevcat_name": "TeV J1442-6226",
            "classes": "",
            "tgevcat_id": 70,
            "gamma_names": "",
            "tevcat2_id": "gc4bRT",
            "tevcat_name": "TeV J1442-624",
            "where": "",
            "other_names": "",
            "discovery_date": "",
            "notes": "",
            "seen_by": ""
        },
        {
            "source_id": 71,
            "tevcat_id": 85,
            "discoverer": "",
            "common_name": "",
            "papers": "",
            "tgevcat_name": "TeV J1442+1200",
            "classes": "",
            "tgevcat_id": 71,
            "gamma_names": "",
            "tevcat2_id": "57tu8J",
            "tevcat_name": "TeV J1443+120",
            "where": "",
            "other_names": "",
            "discovery_date": "",
            "notes": "",
            "seen_by": ""
        },
        {
            "source_id": 72,
            "tevcat_id": 222,
            "discoverer": "",
            "common_name": "",
            "papers": "",
            "tgevcat_name": "TeV J1457-5928",
            "classes": "",
            "tgevcat_id": 72,
            "gamma_names": "",
            "tevcat2_id": "MN9aoz",
            "tevcat_name": "TeV J1457-594",
            "where": "",
            "other_names": "",
            "discovery_date": "",
            "notes": "",
            "seen_by": ""
        },
        {
            "source_id": 73,
            "tevcat_id": 241,
            "discoverer": "",
            "common_name": "",
            "papers": "",
            "tgevcat_name": "TeV J1458-6052",
            "classes": "",
            "tgevcat_id": 73,
            "gamma_names": "",
            "tevcat2_id": "hksZjo",
            "tevcat_name": "TeV J1459-608",
            "where": "",
            "other_names": "",
            "discovery_date": "",
            "notes": "",
            "seen_by": ""
        },
        {
            "source_id": 74,
            "tevcat_id": 171,
            "discoverer": "",
            "common_name": "",
            "papers": "",
            "tgevcat_name": "TeV J1502-4107",
            "classes": "",
            "tgevcat_id": 74,
            "gamma_names": "",
            "tevcat2_id": "lys1PH",
            "tevcat_name": "TeV J1502-421",
            "where": "",
            "other_names": "",
            "discovery_date": "",
            "notes": "",
            "seen_by": ""
        },
        {
            "source_id": 75,
            "tevcat_id": 169,
            "discoverer": "",
            "common_name": "",
            "papers": "",
            "tgevcat_name": "TeV J1503-5813",
            "classes": "",
            "tgevcat_id": 75,
            "gamma_names": "",
            "tevcat2_id": "LuGtCl",
            "tevcat_name": "TeV J1503-582",
            "where": "",
            "other_names": "",
            "discovery_date": "",
            "notes": "",
            "seen_by": ""
        },
        {
            "source_id": 76,
            "tevcat_id": 221,
            "discoverer": "",
            "common_name": "",
            "papers": "",
            "tgevcat_name": "TeV J1504-4148",
            "classes": "",
            "tgevcat_id": 76,
            "gamma_names": "",
            "tevcat2_id": "JbSjYy",
            "tevcat_name": "TeV J1504-418",
            "where": "",
            "other_names": "",
            "discovery_date": "",
            "notes": "",
            "seen_by": ""
        },
        {
            "source_id": 77,
            "tevcat_id": 204,
            "discoverer": "",
            "common_name": "",
            "papers": "",
            "tgevcat_name": "TeV J1506-6221",
            "classes": "",
            "tgevcat_id": 77,
            "gamma_names": "",
            "tevcat2_id": "jNYEaw",
            "tevcat_name": "TeV J1506-623",
            "where": "",
            "other_names": "",
            "discovery_date": "",
            "notes": "",
            "seen_by": ""
        },
        {
            "source_id": 78,
            "tevcat_id": 206,
            "discoverer": "",
            "common_name": "",
            "papers": "",
            "tgevcat_name": "TeV J1512-0906",
            "classes": "",
            "tgevcat_id": 78,
            "gamma_names": "",
            "tevcat2_id": "hptayL",
            "tevcat_name": "TeV J1512-091",
            "where": "",
            "other_names": "",
            "discovery_date": "",
            "notes": "",
            "seen_by": ""
        },
        {
            "source_id": 79,
            "tevcat_id": 95,
            "discoverer": "cangaroo",
            "common_name": "MSH 15-5-02",
            "papers": "2005A&A...435L..17A,2013ApJ...773...77A",
            "tgevcat_name": "TeV J1513-5914",
            "classes": [
                "pwn"
            ],
            "tgevcat_id": 79,
            "gamma_names": [
                "HESS J1514-591"
            ],
            "tevcat2_id": "OhJ7Hr",
            "tevcat_name": "TeV J1514-591",
            "where": "gal",
            "other_names": [
                "SNR G320.3-01.1"
            ],
            "discovery_date": "",
            "notes": "",
            "seen_by": [
                "cangaroo",
                "hess"
            ]
        },
        {
            "source_id": 80,
            "tevcat_id": 202,
            "discoverer": "",
            "common_name": "",
            "papers": "",
            "tgevcat_name": "TeV J1517-2422",
            "classes": "",
            "tgevcat_id": 80,
            "gamma_names": "",
            "tevcat2_id": "qpaBdR",
            "tevcat_name": "TeV J1517-243",
            "where": "",
            "other_names": "",
            "discovery_date": "",
            "notes": "",
            "seen_by": ""
        },
        {
            "source_id": 81,
            "tevcat_id": 235,
            "discoverer": "",
            "common_name": "",
            "papers": "",
            "tgevcat_name": "TeV J1554-5505",
            "classes": "",
            "tgevcat_id": 81,
            "gamma_names": "",
            "tevcat2_id": "Xq3nlo",
            "tevcat_name": "TeV J1554-550",
            "where": "",
            "other_names": "",
            "discovery_date": "",
            "notes": "",
            "seen_by": ""
        },
        {
            "source_id": 82,
            "tevcat_id": 102,
            "discoverer": "",
            "common_name": "",
            "papers": "",
            "tgevcat_name": "TeV J1555+1111",
            "classes": "",
            "tgevcat_id": 82,
            "gamma_names": "",
            "tevcat2_id": "ffHtfX",
            "tevcat_name": "TeV J1555+111",
            "where": "",
            "other_names": "",
            "discovery_date": "",
            "notes": "",
            "seen_by": ""
        },
        {
            "source_id": 83,
            "tevcat_id": 234,
            "discoverer": "",
            "common_name": "",
            "papers": "2011A&A...531L..18H,2014MNRAS.445.2842B,2013A&A...551A..26H,2013MmSAI..84..236M,2013MNRAS.432.3462Z,2011ICRC....7..119D,2011A&A...533L...5D",
            "tgevcat_name": "TeV J1614-5149",
            "classes": "",
            "tgevcat_id": 83,
            "gamma_names": "",
            "tevcat2_id": "ChXqoJ",
            "tevcat_name": "TeV J1614-518",
            "where": "",
            "other_names": "",
            "discovery_date": "",
            "notes": "",
            "seen_by": ""
        },
        {
            "source_id": 84,
            "tevcat_id": 104,
            "discoverer": "",
            "common_name": "",
            "papers": "",
            "tgevcat_name": "TeV J1616-5054",
            "classes": "",
            "tgevcat_id": 84,
            "gamma_names": "",
            "tevcat2_id": "2m5UkC",
            "tevcat_name": "TeV J1616-508",
            "where": "",
            "other_names": "",
            "discovery_date": "",
            "notes": "",
            "seen_by": ""
        },
        {
            "source_id": 85,
            "tevcat_id": 137,
            "discoverer": "",
            "common_name": "",
            "papers": "",
            "tgevcat_name": "TeV J1626-4905",
            "classes": "",
            "tgevcat_id": 85,
            "gamma_names": "",
            "tevcat2_id": "ctBOIp",
            "tevcat_name": "TeV J1626-490",
            "where": "",
            "other_names": "",
            "discovery_date": "",
            "notes": "",
            "seen_by": ""
        },
        {
            "source_id": 86,
            "tevcat_id": 105,
            "discoverer": "",
            "common_name": "",
            "papers": "",
            "tgevcat_name": "TeV J1632-4749",
            "classes": "",
            "tgevcat_id": 86,
            "gamma_names": "",
            "tevcat2_id": "p9DNQ0",
            "tevcat_name": "TeV J1632-478",
            "where": "",
            "other_names": "",
            "discovery_date": "",
            "notes": "",
            "seen_by": ""
        },
        {
            "source_id": 87,
            "tevcat_id": 106,
            "discoverer": "",
            "common_name": "",
            "papers": "",
            "tgevcat_name": "TeV J1634-4716",
            "classes": "",
            "tgevcat_id": 87,
            "gamma_names": "",
            "tevcat2_id": "qne6F2",
            "tevcat_name": "TeV J1634-472",
            "where": "",
            "other_names": "",
            "discovery_date": "",
            "notes": "",
            "seen_by": ""
        },
        {
            "source_id": 88,
            "tevcat_id": 107,
            "discoverer": "",
            "common_name": "",
            "papers": "",
            "tgevcat_name": "TeV J1640-4631",
            "classes": "",
            "tgevcat_id": 88,
            "gamma_names": "",
            "tevcat2_id": "QAgfnh",
            "tevcat_name": "TeV J1640-465",
            "where": "",
            "other_names": "",
            "discovery_date": "",
            "notes": "",
            "seen_by": ""
        },
        {
            "source_id": 89,
            "tevcat_id": 243,
            "discoverer": "",
            "common_name": "",
            "papers": "",
            "tgevcat_name": "TeV J1641-4618",
            "classes": "",
            "tgevcat_id": 89,
            "gamma_names": "",
            "tevcat2_id": "oeIIrE",
            "tevcat_name": "TeV J1641-463",
            "where": "",
            "other_names": "",
            "discovery_date": "",
            "notes": "",
            "seen_by": ""
        },
        {
            "source_id": 90,
            "tevcat_id": 186,
            "discoverer": "",
            "common_name": "",
            "papers": "",
            "tgevcat_name": "TeV J1646-4549",
            "classes": "",
            "tgevcat_id": 90,
            "gamma_names": "",
            "tevcat2_id": "Lv6nKy",
            "tevcat_name": "TeV J1647-458",
            "where": "",
            "other_names": "",
            "discovery_date": "",
            "notes": "",
            "seen_by": ""
        },
        {
            "source_id": 91,
            "tevcat_id": 76,
            "discoverer": "",
            "common_name": "",
            "papers": "",
            "tgevcat_name": "TeV J1653+3945",
            "classes": "",
            "tgevcat_id": 91,
            "gamma_names": "",
            "tevcat2_id": "FItw4l",
            "tevcat_name": "TeV J1653+397",
            "where": "",
            "other_names": "",
            "discovery_date": "",
            "notes": "",
            "seen_by": ""
        },
        {
            "source_id": 92,
            "tevcat_id": 108,
            "discoverer": "",
            "common_name": "",
            "papers": "",
            "tgevcat_name": "TeV J1702-4200",
            "classes": "",
            "tgevcat_id": 92,
            "gamma_names": "",
            "tevcat2_id": "B41Y7y",
            "tevcat_name": "TeV J1702-420",
            "where": "",
            "other_names": "",
            "discovery_date": "",
            "notes": "",
            "seen_by": ""
        },
        {
            "source_id": 93,
            "tevcat_id": 109,
            "discoverer": "",
            "common_name": "",
            "papers": "",
            "tgevcat_name": "TeV J1708-4105",
            "classes": "",
            "tgevcat_id": 93,
            "gamma_names": "",
            "tevcat2_id": "xGSgEi",
            "tevcat_name": "TeV J1708-410",
            "where": "",
            "other_names": "",
            "discovery_date": "",
            "notes": "",
            "seen_by": ""
        },
        {
            "source_id": 94,
            "tevcat_id": 191,
            "discoverer": "",
            "common_name": "",
            "papers": "",
            "tgevcat_name": "TeV J1708-4420",
            "classes": "",
            "tgevcat_id": 94,
            "gamma_names": "",
            "tevcat2_id": "jrf7QE",
            "tevcat_name": "TeV J1708-443",
            "where": "",
            "other_names": "",
            "discovery_date": "",
            "notes": "",
            "seen_by": ""
        },
        {
            "source_id": 95,
            "tevcat_id": 110,
            "discoverer": "",
            "common_name": "",
            "papers": "",
            "tgevcat_name": "TeV J1713-3811",
            "classes": "",
            "tgevcat_id": 95,
            "gamma_names": "",
            "tevcat2_id": "QYavG5",
            "tevcat_name": "TeV J1713-382",
            "where": "",
            "other_names": "",
            "discovery_date": "",
            "notes": "",
            "seen_by": ""
        },
        {
            "source_id": 96,
            "tevcat_id": 84,
            "discoverer": "",
            "common_name": "",
            "papers": "",
            "tgevcat_name": "TeV J1713-3945",
            "classes": "",
            "tgevcat_id": 96,
            "gamma_names": "",
            "tevcat2_id": "Q6SXwo",
            "tevcat_name": "TeV J1713-397",
            "where": "",
            "other_names": "",
            "discovery_date": "",
            "notes": "",
            "seen_by": ""
        },
        {
            "source_id": 97,
            "tevcat_id": 158,
            "discoverer": "",
            "common_name": "",
            "papers": "",
            "tgevcat_name": "TeV J1714-3834",
            "classes": "",
            "tgevcat_id": 97,
            "gamma_names": "",
            "tevcat2_id": "Mk4fht",
            "tevcat_name": "TeV J1714-385",
            "where": "",
            "other_names": "",
            "discovery_date": "",
            "notes": "",
            "seen_by": ""
        },
        {
            "source_id": 98,
            "tevcat_id": 250,
            "discoverer": "",
            "common_name": "",
            "papers": "",
            "tgevcat_name": "TeV J1717-3726",
            "classes": "",
            "tgevcat_id": 98,
            "gamma_names": "",
            "tevcat2_id": "D5Wki5",
            "tevcat_name": "TeV J1718-374",
            "where": "",
            "other_names": "",
            "discovery_date": "",
            "notes": "",
            "seen_by": ""
        },
        {
            "source_id": 99,
            "tevcat_id": 154,
            "discoverer": "",
            "common_name": "",
            "papers": "",
            "tgevcat_name": "TeV J1718-3833",
            "classes": "",
            "tgevcat_id": 99,
            "gamma_names": "",
            "tevcat2_id": "iq0QXk",
            "tevcat_name": "TeV J1718-385",
            "where": "",
            "other_names": "",
            "discovery_date": "",
            "notes": "",
            "seen_by": ""
        },
        {
            "source_id": 100,
            "tevcat_id": 246,
            "discoverer": "",
            "common_name": "",
            "papers": "",
            "tgevcat_name": "TeV J1725+1152",
            "classes": "",
            "tgevcat_id": 100,
            "gamma_names": "",
            "tevcat2_id": "neQBRF",
            "tevcat_name": "TeV 1725+118",
            "where": "",
            "other_names": "",
            "discovery_date": "",
            "notes": "",
            "seen_by": ""
        },
        {
            "source_id": 101,
            "tevcat_id": 232,
            "discoverer": "",
            "common_name": "",
            "papers": "",
            "tgevcat_name": "TeV J1728+5013",
            "classes": "",
            "tgevcat_id": 101,
            "gamma_names": "",
            "tevcat2_id": "9xaXCk",
            "tevcat_name": "TeV J1728+502",
            "where": "",
            "other_names": "",
            "discovery_date": "",
            "notes": "",
            "seen_by": ""
        },
        {
            "source_id": 102,
            "tevcat_id": 224,
            "discoverer": "",
            "common_name": "",
            "papers": "",
            "tgevcat_name": "TeV J1729-3432",
            "classes": "",
            "tgevcat_id": 102,
            "gamma_names": "",
            "tevcat2_id": "UnsKSi",
            "tevcat_name": "TeV J1729-345",
            "where": "",
            "other_names": "",
            "discovery_date": "",
            "notes": "",
            "seen_by": ""
        },
        {
            "source_id": 103,
            "tevcat_id": 141,
            "discoverer": "",
            "common_name": "",
            "papers": "",
            "tgevcat_name": "TeV J1732-3445",
            "classes": "",
            "tgevcat_id": 103,
            "gamma_names": "",
            "tevcat2_id": "mrGXwA",
            "tevcat_name": "TeV J1732-347",
            "where": "",
            "other_names": "",
            "discovery_date": "",
            "notes": "",
            "seen_by": ""
        },
        {
            "source_id": 104,
            "tevcat_id": 189,
            "discoverer": "",
            "common_name": "",
            "papers": "",
            "tgevcat_name": "TeV J1741-3012",
            "classes": "",
            "tgevcat_id": 104,
            "gamma_names": "",
            "tevcat2_id": "JPcqWZ",
            "tevcat_name": "TeV J1741-301",
            "where": "",
            "other_names": "",
            "discovery_date": "",
            "notes": "",
            "seen_by": ""
        },
        {
            "source_id": 105,
            "tevcat_id": 225,
            "discoverer": "",
            "common_name": "",
            "papers": "",
            "tgevcat_name": "TeV J1743+1935",
            "classes": "",
            "tgevcat_id": 105,
            "gamma_names": "",
            "tevcat2_id": "Y4DogE",
            "tevcat_name": "TeV J1743+196",
            "where": "",
            "other_names": "",
            "discovery_date": "",
            "notes": "",
            "seen_by": ""
        },
        {
            "source_id": 106,
            "tevcat_id": 81,
            "discoverer": "",
            "common_name": "",
            "papers": "",
            "tgevcat_name": "TeV J1745-2900",
            "classes": "",
            "tgevcat_id": 106,
            "gamma_names": "",
            "tevcat2_id": "UvKbRe",
            "tevcat_name": "TeV J1745-290",
            "where": "",
            "other_names": "",
            "discovery_date": "",
            "notes": "",
            "seen_by": ""
        },
        {
            "source_id": 107,
            "tevcat_id": 121,
            "discoverer": "",
            "common_name": "",
            "papers": "",
            "tgevcat_name": "TeV J1745-2900",
            "classes": "",
            "tgevcat_id": 107,
            "gamma_names": "",
            "tevcat2_id": "PehQOM",
            "tevcat_name": "TeV J1745-290d",
            "where": "",
            "other_names": "",
            "discovery_date": "",
            "notes": "",
            "seen_by": ""
        },
        {
            "source_id": 108,
            "tevcat_id": 111,
            "discoverer": "",
            "common_name": "",
            "papers": "",
            "tgevcat_name": "TeV J1745-3022",
            "classes": "",
            "tgevcat_id": 108,
            "gamma_names": "",
            "tevcat2_id": "Gmuzgm",
            "tevcat_name": "TeV J1745-303",
            "where": "",
            "other_names": "",
            "discovery_date": "",
            "notes": "",
            "seen_by": ""
        },
        {
            "source_id": 109,
            "tevcat_id": 234,
            "discoverer": "",
            "common_name": "",
            "papers": "",
            "tgevcat_name": "TeV J1747-2448",
            "classes": "",
            "tgevcat_id": 109,
            "gamma_names": "",
            "tevcat2_id": "xhmRbS",
            "tevcat_name": "TeV J1747-248",
            "where": "",
            "other_names": "",
            "discovery_date": "",
            "notes": "",
            "seen_by": ""
        },
        {
            "source_id": 110,
            "tevcat_id": 112,
            "discoverer": "",
            "common_name": "",
            "papers": "",
            "tgevcat_name": "TeV J1747-2809",
            "classes": "",
            "tgevcat_id": 110,
            "gamma_names": "",
            "tevcat2_id": "jvz6ag",
            "tevcat_name": "TeV J1747-281",
            "where": "",
            "other_names": "",
            "discovery_date": "",
            "notes": "",
            "seen_by": ""
        },
        {
            "source_id": 111,
            "tevcat_id": 163,
            "discoverer": "hess",
            "common_name": "HESS J1800-240A",
            "papers": "2008A&A...481..401A,2010ApJ...718..348A",
            "tgevcat_name": "TeV J1800-2359",
            "classes": [
                "snr",
                "mc"
            ],
            "tgevcat_id": 111,
            "gamma_names": [
                "HESS J1800-240A"
            ],
            "tevcat2_id": "sPYizN",
            "tevcat_name": "TeV J1801-239",
            "where": "gal",
            "other_names": [
                "W 28",
                "SNR G6.4-0.1"
            ],
            "discovery_date": "",
            "notes": "tgevcat_name: TeV J1800-2359 represents both HESS J1800-240A and HESS J1800-240B.\n",
            "seen_by": [
                "hess"
            ]
        },
        {
            "source_id": 112,
            "tevcat_id": 162,
            "discoverer": "",
            "common_name": "",
            "papers": "",
            "tgevcat_name": "TeV J1801-2320",
            "classes": "",
            "tgevcat_id": 112,
            "gamma_names": "",
            "tevcat2_id": "jcVLu0",
            "tevcat_name": "TeV J1801-233",
            "where": "",
            "other_names": "",
            "discovery_date": "",
            "notes": "",
            "seen_by": ""
        },
        {
            "source_id": 113,
            "tevcat_id": 113,
            "discoverer": "",
            "common_name": "",
            "papers": "",
            "tgevcat_name": "TeV J1804-2143",
            "classes": "",
            "tgevcat_id": 113,
            "gamma_names": "",
            "tevcat2_id": "y1kNQO",
            "tevcat_name": "TeV J1804-217",
            "where": "",
            "other_names": "",
            "discovery_date": "",
            "notes": "",
            "seen_by": ""
        },
        {
            "source_id": 114,
            "tevcat_id": 242,
            "discoverer": "",
            "common_name": "",
            "papers": "",
            "tgevcat_name": "TeV J1808-2026",
            "classes": "",
            "tgevcat_id": 114,
            "gamma_names": "",
            "tevcat2_id": "Ere9PS",
            "tevcat_name": "TeV J1808-204",
            "where": "",
            "other_names": "",
            "discovery_date": "",
            "notes": "",
            "seen_by": ""
        },
        {
            "source_id": 115,
            "tevcat_id": 155,
            "discoverer": "",
            "common_name": "",
            "papers": "",
            "tgevcat_name": "TeV J1810-1918",
            "classes": "",
            "tgevcat_id": 115,
            "gamma_names": "",
            "tevcat2_id": "OWsjG1",
            "tevcat_name": "TeV J1810-193",
            "where": "",
            "other_names": "",
            "discovery_date": "",
            "notes": "",
            "seen_by": ""
        },
        {
            "source_id": 116,
            "tevcat_id": 114,
            "discoverer": "",
            "common_name": "",
            "papers": "",
            "tgevcat_name": "TeV J1813-1750",
            "classes": "",
            "tgevcat_id": 116,
            "gamma_names": "",
            "tevcat2_id": "Unhlxa",
            "tevcat_name": "TeV J1813-178",
            "where": "",
            "other_names": "",
            "discovery_date": "",
            "notes": "",
            "seen_by": ""
        },
        {
            "source_id": 117,
            "tevcat_id": 233,
            "discoverer": "",
            "common_name": "",
            "papers": "",
            "tgevcat_name": "TeV J1818-1528",
            "classes": "",
            "tgevcat_id": 117,
            "gamma_names": "",
            "tevcat2_id": "SxYdrN",
            "tevcat_name": "TeV J1818-154",
            "where": "",
            "other_names": "",
            "discovery_date": "",
            "notes": "",
            "seen_by": ""
        },
        {
            "source_id": 118,
            "tevcat_id": 115,
            "discoverer": "",
            "common_name": "",
            "papers": "",
            "tgevcat_name": "TeV J1825-1350",
            "classes": "",
            "tgevcat_id": 118,
            "gamma_names": "",
            "tevcat2_id": "xnwQAv",
            "tevcat_name": "TeV J1826-137",
            "where": "",
            "other_names": "",
            "discovery_date": "",
            "notes": "",
            "seen_by": ""
        },
        {
            "source_id": 119,
            "tevcat_id": 96,
            "discoverer": "",
            "common_name": "",
            "papers": "",
            "tgevcat_name": "TeV J1826-1449",
            "classes": "",
            "tgevcat_id": 119,
            "gamma_names": "",
            "tevcat2_id": "xKaTtF",
            "tevcat_name": "TeV J1826-148",
            "where": "",
            "other_names": "",
            "discovery_date": "",
            "notes": "",
            "seen_by": ""
        },
        {
            "source_id": 120,
            "tevcat_id": 231,
            "discoverer": "",
            "common_name": "",
            "papers": "",
            "tgevcat_name": "TeV J1831-0954",
            "classes": "",
            "tgevcat_id": 120,
            "gamma_names": "",
            "tevcat2_id": "buLRDe",
            "tevcat_name": "TeV J1831-099",
            "where": "",
            "other_names": "",
            "discovery_date": "",
            "notes": "",
            "seen_by": ""
        },
        {
            "source_id": 122,
            "tevcat_id": 230,
            "discoverer": "",
            "common_name": "",
            "papers": "",
            "tgevcat_name": "TeV J1832-0922",
            "classes": "",
            "tgevcat_id": 122,
            "gamma_names": "",
            "tevcat2_id": "1aPLDl",
            "tevcat_name": "TeV J1832-093",
            "where": "",
            "other_names": "",
            "discovery_date": "",
            "notes": "",
            "seen_by": ""
        },
        {
            "source_id": 122,
            "tevcat_id": 140,
            "discoverer": "",
            "common_name": "",
            "papers": "",
            "tgevcat_name": "TeV J1833-1033",
            "classes": "",
            "tgevcat_id": 122,
            "gamma_names": "",
            "tevcat2_id": "EmvcSG",
            "tevcat_name": "TeV J1833-105",
            "where": "",
            "other_names": "",
            "discovery_date": "",
            "notes": "",
            "seen_by": ""
        },
        {
            "source_id": 123,
            "tevcat_id": 116,
            "discoverer": "",
            "common_name": "",
            "papers": "",
            "tgevcat_name": "TeV J1834-0845",
            "classes": "",
            "tgevcat_id": 123,
            "gamma_names": "",
            "tevcat2_id": "4xiQfb",
            "tevcat_name": "TeV J1834-087",
            "where": "",
            "other_names": "",
            "discovery_date": "",
            "notes": "",
            "seen_by": ""
        },
        {
            "source_id": 124,
            "tevcat_id": 117,
            "discoverer": "",
            "common_name": "",
            "papers": "",
            "tgevcat_name": "TeV J1837-0656",
            "classes": "",
            "tgevcat_id": 124,
            "gamma_names": "",
            "tevcat2_id": "giVWlK",
            "tevcat_name": "TeV J1837-069",
            "where": "",
            "other_names": "",
            "discovery_date": "",
            "notes": "",
            "seen_by": ""
        },
        {
            "source_id": 125,
            "tevcat_id": 142,
            "discoverer": "",
            "common_name": "",
            "papers": "",
            "tgevcat_name": "TeV J1840-0533",
            "classes": "",
            "tgevcat_id": 125,
            "gamma_names": "",
            "tevcat2_id": "amNIwH",
            "tevcat_name": "TeV J1840-055",
            "where": "",
            "other_names": "",
            "discovery_date": "",
            "notes": "",
            "seen_by": ""
        },
        {
            "source_id": 126,
            "tevcat_id": 190,
            "discoverer": "",
            "common_name": "",
            "papers": "",
            "tgevcat_name": "TeV J1843-0318",
            "classes": "",
            "tgevcat_id": 126,
            "gamma_names": "",
            "tevcat2_id": "DTC72E",
            "tevcat_name": "TeV J1843-030",
            "where": "",
            "other_names": "",
            "discovery_date": "",
            "notes": "",
            "seen_by": ""
        },
        {
            "source_id": 127,
            "tevcat_id": 167,
            "discoverer": "",
            "common_name": "",
            "papers": "",
            "tgevcat_name": "TeV J1846-0258",
            "classes": "",
            "tgevcat_id": 127,
            "gamma_names": "",
            "tevcat2_id": "Ipmg1A",
            "tevcat_name": "TeV J1846-029",
            "where": "",
            "other_names": "",
            "discovery_date": "",
            "notes": "",
            "seen_by": ""
        },
        {
            "source_id": 128,
            "tevcat_id": 187,
            "discoverer": "",
            "common_name": "",
            "papers": "",
            "tgevcat_name": "TeV J1848-0147",
            "classes": "",
            "tgevcat_id": 128,
            "gamma_names": "",
            "tevcat2_id": "hcE3Ou",
            "tevcat_name": "TeV J1848-017",
            "where": "",
            "other_names": "",
            "discovery_date": "",
            "notes": "",
            "seen_by": ""
        },
        {
            "source_id": 129,
            "tevcat_id": 188,
            "discoverer": "",
            "common_name": "",
            "papers": "",
            "tgevcat_name": "TeV J1849-0001",
            "classes": "",
            "tgevcat_id": 129,
            "gamma_names": "",
            "tevcat2_id": "8nWF6I",
            "tevcat_name": "TeV J1849-000",
            "where": "",
            "other_names": "",
            "discovery_date": "",
            "notes": "",
            "seen_by": ""
        },
        {
            "source_id": 130,
            "tevcat_id": 143,
            "discoverer": "hess",
            "common_name": "HESS J1857+026",
            "papers": "2008A&A...477..353A,2014A&A...571A..96M",
            "tgevcat_name": "TeV J1857+0242",
            "classes": [
                "unid"
            ],
            "tgevcat_id": 130,
            "gamma_names": [
                "MAGIC J1857.2+0263",
                "MAGIC J1857.6+0297",
                "1HWC J1857+023"
            ],
            "tevcat2_id": "BDIaeo",
            "tevcat_name": "TeV J1857+026",
            "where": "gal",
            "other_names": [],
            "discovery_date": "",
            "notes": "",
            "seen_by": [
                "hess",
                "magic",
                "hawc"
            ]
        },
        {
            "source_id": 131,
            "tevcat_id": 144,
            "discoverer": "hess",
            "common_name": "HESS J1858+020",
            "papers": "2008A&A...477..353A,2016ApJ...817....3A,2014ApJ...787..166A",
            "tgevcat_name": "TeV J1858+0205",
            "classes": [
                "unid"
            ],
            "tgevcat_id": 131,
            "gamma_names": [
                "1HWC J1857+023"
            ],
            "tevcat2_id": "KxJfNI",
            "tevcat_name": "TeV J1858+020",
            "where": "gal",
            "other_names": [
                "G35.6-0.4"
            ],
            "discovery_date": "",
            "notes": "",
            "seen_by": [
                "hess",
                "hawc"
            ]
        },
        {
            "source_id": 132,
            "tevcat_id": 148,
            "discoverer": "milagro",
            "common_name": "MGRO J1908+06",
            "papers": "2007arXiv0710.4057T,2009A&A...499..723A",
            "tgevcat_name": "TeV J1907+0613",
            "classes": [
                "unid"
            ],
            "tgevcat_id": 132,
            "gamma_names": [
                "HESS J1908+063",
                "VER J1907+062",
                "1HWC J1907+062c",
                "ARGO J1907+0627",
                "ARGO J1910+0720"
            ],
            "tevcat2_id": "eaYOuH",
            "tevcat_name": "TeV J1907+062",
            "where": "gal",
            "other_names": [
                "GeV J1907+0557",
                "GRO J1908+0556",
                "G40.5-0.5",
                "0FGL J1907.5+0602",
                "1AGL J1908+0613"
            ],
            "discovery_date": "",
            "notes": "",
            "seen_by": [
                "hess",
                "milagro",
                "veritas",
                "hawc",
                "argo"
            ]
        },
        {
            "source_id": 133,
            "tevcat_id": 218,
            "discoverer": "hess",
            "common_name": "W 49B",
            "papers": "2011arXiv1104.5003B,2011ICRC....7..111B,2016arXiv160900600H",
            "tgevcat_name": "TeV J1911+0905",
            "classes": [
                "snr",
                "mc"
            ],
            "tgevcat_id": 133,
            "gamma_names": [
                "HESS J1911+090"
            ],
            "tevcat2_id": "tHQw4n",
            "tevcat_name": "TeV J1911+090",
            "where": "gal",
            "other_names": [
                "SNR G043.3-00.2",
                "0FGL J1911.0+0905",
                "1FGL J1910.9+0906c"
            ],
            "discovery_date": "",
            "notes": "",
            "seen_by": [
                "hess"
            ]
        },
        {
            "source_id": 134,
            "tevcat_id": 157,
            "discoverer": "hess",
            "common_name": "HESS J1912+101",
            "papers": "2008A&A...484..435A",
            "tgevcat_name": "TeV J1912+1009",
            "classes": [
                "pwn"
            ],
            "tgevcat_id": 134,
            "gamma_names": [],
            "tevcat2_id": "J26r5R",
            "tevcat_name": "TeV J1912+101",
            "where": "gal",
            "other_names": [
                "PSR J1913+1011"
            ],
            "discovery_date": "",
            "notes": "",
            "seen_by": [
                "hess"
            ]
        },
        {
            "source_id": 135,
            "tevcat_id": 178,
            "discoverer": "hess",
            "common_name": "W 51C",
            "papers": "2012A&A...541A..13A",
            "tgevcat_name": "TeV J1922+1411",
            "classes": [
                "snr",
                "mc"
            ],
            "tgevcat_id": 135,
            "gamma_names": [
                "HESS J1923+141"
            ],
            "tevcat2_id": "ParXkE",
            "tevcat_name": "TeV J1923+141",
            "where": "gal",
            "other_names": [
                "SNR G49.2-0.7",
                "0FGL J1923.0+1411"
            ],
            "discovery_date": "",
            "notes": "",
            "seen_by": [
                "hess",
                "magic",
                "milagro"
            ]
        },
        {
            "source_id": 136,
            "tevcat_id": 193,
            "discoverer": "veritas",
            "common_name": "SNR G054.1+00.3",
            "papers": "2010ApJ...719L..69A",
            "tgevcat_name": "TeV J1930+1852",
            "classes": [
                "pwn",
                "snr"
            ],
            "tgevcat_id": 136,
            "gamma_names": [
                "VER J1930+188"
            ],
            "tevcat2_id": "F0Luol",
            "tevcat_name": "TeV J1930+188",
            "where": "gal",
            "other_names": [
                "PSR J1930+1852"
            ],
            "discovery_date": "",
            "notes": "",
            "seen_by": [
                "veritas"
            ]
        },
        {
            "source_id": 137,
            "tevcat_id": 214,
            "discoverer": "hess",
            "common_name": "HESS J1943+213",
            "papers": "2011A&A...529A..49H",
            "tgevcat_name": "TeV J1943+2118",
            "classes": [
                "hbl"
            ],
            "tgevcat_id": 137,
            "gamma_names": [],
            "tevcat2_id": "RdzX69",
            "tevcat_name": "TeV J1943+213",
            "where": "egal",
            "other_names": [],
            "discovery_date": "",
            "notes": "",
            "seen_by": [
                "hess",
                "veritas"
            ]
        },
        {
            "source_id": 138,
            "tevcat_id": 79,
            "discoverer": "magic",
            "common_name": "1ES 1959+650",
            "papers": "2006ApJ...639..761A",
            "tgevcat_name": "TeV J1959+6508",
            "classes": [
                "hbl"
            ],
            "tgevcat_id": 138,
            "gamma_names": [],
            "tevcat2_id": "cUkkpO",
            "tevcat_name": "TeV J1959+651",
            "where": "egal",
            "other_names": [],
            "discovery_date": "",
            "notes": "",
            "seen_by": [
                "magic",
                "veritas",
                "hegra"
            ]
        },
        {
            "source_id": 139,
            "tevcat_id": 165,
            "discoverer": "magic",
            "common_name": "MAGIC J2001+435",
            "papers": "2010ATel.2753....1M",
            "tgevcat_name": "TeV J2001+4353",
            "classes": [
                "ibl"
            ],
            "tgevcat_id": 139,
            "gamma_names": [],
            "tevcat2_id": "ljNqkw",
            "tevcat_name": "TeV J2001+438",
            "where": "egal",
            "other_names": [
                "1FGL J2001.1+4351",
                "MG4 J200112+4352"
            ],
            "discovery_date": "",
            "notes": "",
            "seen_by": [
                "magic"
            ]
        },
        {
            "source_id": 140,
            "tevcat_id": 100,
            "discoverer": "hess",
            "common_name": "PKS 2005-489",
            "papers": "2005A&A...436L..17A,2010A&A...511A..52H,2011A&A...533A.110H",
            "tgevcat_name": "TeV J2009-4849",
            "classes": [
                "hbl"
            ],
            "tgevcat_id": 140,
            "gamma_names": [
                "HESS J2009-488"
            ],
            "tevcat2_id": "ObIXbg",
            "tevcat_name": "TeV J2009-488",
            "where": "egal",
            "other_names": [],
            "discovery_date": "",
            "notes": "",
            "seen_by": [
                "hess"
            ]
        },
        {
            "source_id": 141,
            "tevcat_id": 228,
            "discoverer": "veritas",
            "common_name": "VER J2016+371",
            "papers": "2014ApJ...788...78A",
            "tgevcat_name": "TeV J2016+3711",
            "classes": [
                "pwn",
                "snr"
            ],
            "tgevcat_id": 141,
            "gamma_names": [
                "MGRO J2019+37"
            ],
            "tevcat2_id": "wbkK3X",
            "tevcat_name": "TeV J2016+372",
            "where": "gal",
            "other_names": [
                "CTB 87"
            ],
            "discovery_date": "",
            "notes": "",
            "seen_by": [
                "veritas",
                "milagro"
            ]
        },
        {
            "source_id": 142,
            "tevcat_id": 145,
            "discoverer": "milagro",
            "common_name": "Dragonfly",
            "papers": "2012ApJ...753..159A,2007ApJ...658L..33A",
            "tgevcat_name": "TeV J2018+3642",
            "classes": [
                "pwn",
                "unid"
            ],
            "tgevcat_id": 142,
            "gamma_names": [
                "MGRO J2019+37",
                "VER J2019+368",
                "VER J2016+371"
            ],
            "tevcat2_id": "RZ7qzv",
            "tevcat_name": "TeV J2019+368",
            "where": "gal",
            "other_names": [
                "0FGL J2020.8+3649"
            ],
            "discovery_date": "",
            "notes": "",
            "seen_by": [
                "milagro",
                "veritas"
            ]
        },
        {
            "source_id": 143,
            "tevcat_id": 259,
            "discoverer": "veritas",
            "common_name": "VER J2019+368",
            "papers": "2014ApJ...788...78A",
            "tgevcat_name": "TeV J2019+3648",
            "classes": [
                "unid"
            ],
            "tgevcat_id": 143,
            "gamma_names": [
                "MGRO J2019+37"
            ],
            "tevcat2_id": "",
            "tevcat_name": "TeV J2019+368",
            "where": "gal",
            "other_names": [],
            "discovery_date": "",
            "notes": "",
            "seen_by": [
                "veritas"
            ]
        },
        {
            "source_id": 144,
            "tevcat_id": 201,
            "discoverer": "veritas",
            "common_name": "Gamma Cygni",
            "papers": "2013ApJ...770...93A,2011arXiv1111.1034A",
            "tgevcat_name": "TeV J2020+4045",
            "classes": [
                "unid"
            ],
            "tgevcat_id": 144,
            "gamma_names": [
                "VER J2019+407"
            ],
            "tevcat2_id": "IWrXQp",
            "tevcat_name": "TeV J2019+407",
            "where": "gal",
            "other_names": [
                "1FGL J2020.0+4049",
                "SNR G78.2+2.1"
            ],
            "discovery_date": "",
            "notes": "",
            "seen_by": [
                "veritas"
            ]
        },
        {
            "source_id": 145,
            "tevcat_id": 149,
            "discoverer": "milagro",
            "common_name": "MGRO J2031+41",
            "papers": "2009ApJ...700L.127A,2007AIPC..921..172L",
            "tgevcat_name": "TeV J2031+4040",
            "classes": [
                "unid"
            ],
            "tgevcat_id": 145,
            "gamma_names": [],
            "tevcat2_id": "1FCN0q",
            "tevcat_name": "TeV J2031+406",
            "where": "gal",
            "other_names": [
                "TeV J2032+4130",
                "TeV 2032+413",
                "0FGL J2032.2+4122"
            ],
            "discovery_date": "",
            "notes": "",
            "seen_by": [
                "milagro"
            ]
        },
        {
            "source_id": 146,
            "tevcat_id": 87,
            "discoverer": "hegra",
            "common_name": "TeV J2032+4130",
            "papers": "2014ApJ...783...16A,2008ApJ...675L..25A,2003ICRC....4.2345R",
            "tgevcat_name": "TeV J2031+4133",
            "classes": [
                "unid"
            ],
            "tgevcat_id": 146,
            "gamma_names": [
                "MGRO J2031+41"
            ],
            "tevcat2_id": "3IY6Gd",
            "tevcat_name": "TeV J2032+415",
            "where": "gal",
            "other_names": [
                "0FGL J2032.2+4122"
            ],
            "discovery_date": "",
            "notes": "",
            "seen_by": [
                "hegra",
                "veritas",
                "magic",
                "milagro"
            ]
        },
        {
            "source_id": 147,
            "tevcat_id": 90,
            "discoverer": "hess",
            "common_name": "PKS 2155-304",
            "papers": "2005A&A...442..895A,2005A&A...430..865A",
            "tgevcat_name": "TeV J2158-3013",
            "classes": [
                "hbl"
            ],
            "tgevcat_id": 147,
            "gamma_names": [
                "HESS J2158-302"
            ],
            "tevcat2_id": "nm0IZL",
            "tevcat_name": "TeV J2158-302",
            "where": "egal",
            "other_names": [],
            "discovery_date": "",
            "notes": "",
            "seen_by": [
                "hess",
                "magic"
            ]
        },
        {
            "source_id": 148,
            "tevcat_id": 118,
            "discoverer": "crimea",
            "common_name": "BL Lacertae",
            "papers": "2007ApJ...666L..17A",
            "tgevcat_name": "TeV J2202+4216",
            "classes": [
                "lbl"
            ],
            "tgevcat_id": 148,
            "gamma_names": [],
            "tevcat2_id": "iIWshp",
            "tevcat_name": "TeV J2202+422",
            "where": "egal",
            "other_names": [
                "1ES 2200+420"
            ],
            "discovery_date": "",
            "notes": "",
            "seen_by": [
                "crimea",
                "veritas",
                "magic"
            ]
        },
        {
            "source_id": 150,
            "tevcat_id": 182,
            "discoverer": "milagro",
            "common_name": "Boomerang",
            "papers": "2009ApJ...700L.127A",
            "tgevcat_name": "TeV J2228+6110",
            "classes": [
                "pwn",
                "snr"
            ],
            "tgevcat_id": 150,
            "gamma_names": [
                "MGRO C4",
                "MGRO J2228+61"
            ],
            "tevcat2_id": "qsRoN6",
            "tevcat_name": "TeV J2228+611",
            "where": "gal",
            "other_names": [
                "G 106.6+2.9",
                "PSR J2229+6114",
                "0FGL J2229.0+6114"
            ],
            "discovery_date": "",
            "notes": "",
            "seen_by": [
                "milagro"
            ]
        },
        {
            "source_id": 151,
            "tevcat_id": 257,
            "discoverer": "veritas",
            "common_name": "RGB J2243+203",
            "papers": "2015arXiv150806334A,2014ATel.6849....1H",
            "tgevcat_name": "TeV J2243+2021",
            "classes": [
                "ibl"
            ],
            "tgevcat_id": 151,
            "gamma_names": [],
            "tevcat2_id": "7IL8zC",
            "tevcat_name": "TeV J2243+203",
            "where": "egal",
            "other_names": [],
            "discovery_date": "",
            "notes": "",
            "seen_by": [
                "veritas"
            ]
        },
        {
            "source_id": 152,
            "tevcat_id": 211,
            "discoverer": "magic",
            "common_name": "B3 2247+381",
            "papers": "2012A&A...539A.118A",
            "tgevcat_name": "TeV J2250+3824",
            "classes": [
                "hbl"
            ],
            "tgevcat_id": 152,
            "gamma_names": [],
            "tevcat2_id": "WCU2Cw",
            "tevcat_name": "TeV J2250+384",
            "where": "egal",
            "other_names": [],
            "discovery_date": "",
            "notes": "",
            "seen_by": [
                "magic"
            ]
        },
        {
            "source_id": 153,
            "tevcat_id": 82,
            "discoverer": "hegra",
            "common_name": "Cassiopeia A",
            "papers": "2010ApJ...714..163A,2001A&A...370..112A",
            "tgevcat_name": "TeV J2323+5848",
            "classes": [
                "snr"
            ],
            "tgevcat_id": 153,
            "gamma_names": [],
            "tevcat2_id": "3dz45u",
            "tevcat_name": "TeV J2323+588",
            "where": "gal",
            "other_names": [
                "Cas A",
                "3C461",
                "G111.7-2.1"
            ],
            "discovery_date": "",
            "notes": "",
            "seen_by": [
                "hegra",
                "magic",
                "veritas"
            ]
        },
        {
            "source_id": 154,
            "tevcat_id": 77,
            "discoverer": "whipple",
            "common_name": "1ES 2344+514",
            "papers": "1998ApJ...501..616C,2007ApJ...662..892A",
            "tgevcat_name": "TeV J2346+5142",
            "classes": [
                "hbl"
            ],
            "tgevcat_id": 154,
            "gamma_names": [],
            "tevcat2_id": "FcTRDg",
            "tevcat_name": "TeV J2347+517",
            "where": "egal",
            "other_names": [],
            "discovery_date": "",
            "notes": "",
            "seen_by": [
                "whipple",
                "hegra",
                "magic",
                "veritas"
            ]
        },
        {
            "source_id": 155,
            "tevcat_id": 101,
            "discoverer": "hess",
            "common_name": "H 2356-309",
            "papers": "2010A&A...516A..56H,2006A&A...455..461A",
            "tgevcat_name": "TeV J2359-3037",
            "classes": [
                "hbl"
            ],
            "tgevcat_id": 155,
            "gamma_names": [
                "HESS J2359-306"
            ],
            "tevcat2_id": "VIbvxm",
            "tevcat_name": "TeV J2359-306",
            "where": "egal",
            "other_names": [
                "1H 2354-315"
            ],
            "discovery_date": "",
            "notes": "",
            "seen_by": [
                "hess"
            ]
        },
        {
            "source_id": 156,
            "tevcat_id": 164,
            "discoverer": "hess",
            "common_name": "HESS J1800-240B",
            "papers": "2008A&A...481..401A,2016JHEAp..11....1H",
            "tgevcat_name": "TeV J1800-2359",
            "classes": [
                "snr",
                "mc"
            ],
            "tgevcat_id": 111,
            "gamma_names": [
                "HESS J1800-240B"
            ],
            "tevcat2_id": "mxBSx6",
            "tevcat_name": "TeV J1800-240",
            "where": "gal",
            "other_names": [],
            "discovery_date": "",
            "notes": "tgevcat_name: TeV J1800-2359 represents both HESS J1800-240A and HESS J1800-240B.\n",
            "seen_by": [
                "hess"
            ]
        }
    ]
}